107820005/CO_HW1/1.2/HW/clk_divn_5.v
module clk_divn_5(input clk,
output clk_out);
 
wire d2,d1,d0;
reg q2,q1,q0,q2temp;
 
initial begin
q2 = 0;
q1 = 0;
q0 = 0;
end
 
assign q2bar = ~q2;
assign q1bar = ~q1;
assign q0bar = ~q0;
 
assign d0 = q2bar & q0bar;
assign d1 = (q1&q0bar) | (q1bar & q0);
assign d2 = q1 & q0;
//q0
always @(posedge clk) begin
q0 <= d0;
q1 <= d1;
q2 <= d2;
end
always @(negedge clk) begin
q2temp <= q1;
end
assign clk_out = q1 | q2temp;
endmodule

107820005/CO_HW1/1.2/HW/clk_divn_5_tb.v
module clk_divn_5_tb();
reg reset = 0;
initial begin
$dumpfile("clk_divn_5_tb.vcd");
$dumpvars(0,clk_divn_5_tb);
 
# 17 reset = 1;
# 11 reset = 0;
# 29 reset = 1;
# 5 reset =0;
# 513 $finish;
end
 
reg clk = 0;
always #1 clk = !clk;
 
wire clk_out;
clk_divn_5 c1 (.clk(clk),
.clk_out(clk_out));
 
initial
$monitor("At time %t, value = %h (%0d)",
$time, clk_out, clk_out);
endmodule // clk_divn_5_tb

107820005/CO_HW1/1.2/HW/simulation/modelsim/clk_divn_5_tb.vcd
$date
	Wed Apr 15 13:45:18 2020
$end
$version
	ModelSim Version 10.5b
$end
$timescale
	1ps
$end

$scope module clk_divn_5_tb $end
$var reg 1 ! reset $end
$var reg 1 " clk $end
$var wire 1 # clk_out $end

$scope module c1 $end
$var wire 1 $ clk $end
$var wire 1 # clk_out $end
$var wire 1 % d2 $end
$var wire 1 & d1 $end
$var wire 1 ' d0 $end
$var reg 1 ( q2 $end
$var reg 1 ) q1 $end
$var reg 1 * q0 $end
$var reg 1 + q2temp $end
$var wire 1 , q2bar $end
$var wire 1 - q1bar $end
$var wire 1 . q0bar $end
$upscope $end
$upscope $end
$enddefinitions $end
#0
$dumpvars
0!
0"
0(
0)
0*
0+
0#
0%
0&
1'
1,
1-
1.
0$
$end
#1
1"
1$
1*
0.
1&
0'
#2
0"
0$
#3
1"
1$
0*
1)
0-
1#
1.
1'
#4
0"
0$
1+
#5
1"
1$
1*
0.
1%
0'
0&
#6
0"
0$
#7
1"
1$
0*
0)
1(
0,
1-
1.
0%
#8
0"
0$
0+
0#
#9
1"
1$
0(
1,
1'
#10
0"
0$
#11
1"
1$
1*
0.
1&
0'
#12
0"
0$
#13
1"
1$
0*
1)
0-
1#
1.
1'
#14
0"
0$
1+
#15
1"
1$
1*
0.
1%
0'
0&
#16
0"
0$
#17
1!
1"
1$
0*
0)
1(
0,
1-
1.
0%
#18
0"
0$
0+
0#
#19
1"
1$
0(
1,
1'
#20
0"
0$
#21
1"
1$
1*
0.
1&
0'
#22
0"
0$
#23
1"
1$
0*
1)
0-
1#
1.
1'
#24
0"
0$
1+
#25
1"
1$
1*
0.
1%
0'
0&
#26
0"
0$
#27
1"
1$
0*
0)
1(
0,
1-
1.
0%
#28
0!
0"
0$
0+
0#
#29
1"
1$
0(
1,
1'
#30
0"
0$
#31
1"
1$
1*
0.
1&
0'
#32
0"
0$
#33
1"
1$
0*
1)
0-
1#
1.
1'
#34
0"
0$
1+
#35
1"
1$
1*
0.
1%
0'
0&
#36
0"
0$
#37
1"
1$
0*
0)
1(
0,
1-
1.
0%
#38
0"
0$
0+
0#
#39
1"
1$
0(
1,
1'
#40
0"
0$
#41
1"
1$
1*
0.
1&
0'
#42
0"
0$
#43
1"
1$
0*
1)
0-
1#
1.
1'
#44
0"
0$
1+
#45
1"
1$
1*
0.
1%
0'
0&
#46
0"
0$
#47
1"
1$
0*
0)
1(
0,
1-
1.
0%
#48
0"
0$
0+
0#
#49
1"
1$
0(
1,
1'
#50
0"
0$
#51
1"
1$
1*
0.
1&
0'
#52
0"
0$
#53
1"
1$
0*
1)
0-
1#
1.
1'
#54
0"
0$
1+
#55
1"
1$
1*
0.
1%
0'
0&
#56
0"
0$
#57
1!
1"
1$
0*
0)
1(
0,
1-
1.
0%
#58
0"
0$
0+
0#
#59
1"
1$
0(
1,
1'
#60
0"
0$
#61
1"
1$
1*
0.
1&
0'
#62
0!
0"
0$
#63
1"
1$
0*
1)
0-
1#
1.
1'
#64
0"
0$
1+
#65
1"
1$
1*
0.
1%
0'
0&
#66
0"
0$
#67
1"
1$
0*
0)
1(
0,
1-
1.
0%
#68
0"
0$
0+
0#
#69
1"
1$
0(
1,
1'
#70
0"
0$
#71
1"
1$
1*
0.
1&
0'
#72
0"
0$
#73
1"
1$
0*
1)
0-
1#
1.
1'
#74
0"
0$
1+
#75
1"
1$
1*
0.
1%
0'
0&
#76
0"
0$
#77
1"
1$
0*
0)
1(
0,
1-
1.
0%
#78
0"
0$
0+
0#
#79
1"
1$
0(
1,
1'
#80
0"
0$
#81
1"
1$
1*
0.
1&
0'
#82
0"
0$
#83
1"
1$
0*
1)
0-
1#
1.
1'
#84
0"
0$
1+
#85
1"
1$
1*
0.
1%
0'
0&
#86
0"
0$
#87
1"
1$
0*
0)
1(
0,
1-
1.
0%
#88
0"
0$
0+
0#
#89
1"
1$
0(
1,
1'
#90
0"
0$
#91
1"
1$
1*
0.
1&
0'
#92
0"
0$
#93
1"
1$
0*
1)
0-
1#
1.
1'
#94
0"
0$
1+
#95
1"
1$
1*
0.
1%
0'
0&
#96
0"
0$
#97
1"
1$
0*
0)
1(
0,
1-
1.
0%
#98
0"
0$
0+
0#
#99
1"
1$
0(
1,
1'
